mkdocs_tooltips/__init__.py
mkdocs_tooltips/plugin.py
mkdocs_tooltips-0.1.0.dist-info/entry_points.txt
mkdocs_tooltips-0.1.0.dist-info/WHEEL
mkdocs_tooltips-0.1.0.dist-info/METADATA
mkdocs_tooltips-0.1.0.dist-info/RECORD
