Metadata-Version: 2.1
Name: mkdocs-tooltips
Version: 0.1.0
Summary: Add and customize tooltips in MkDocs.
Keywords: mkdocs,mkdocs-plugin
Author: Nathanaël
Author-email: roipoussiere@protonmail.com
Requires-Python: >=3.6,<4.0
Classifier: Programming Language :: Python :: 3
Classifier: Programming Language :: Python :: 3.6
Classifier: Programming Language :: Python :: 3.7
Classifier: Programming Language :: Python :: 3.8
Classifier: Programming Language :: Python :: 3.9
Requires-Dist: mkdocs (>=1.1.2,<2.0.0)
